downloadx/__init__.py
downloadx/__main__.py
downloadx/_typed.py
downloadx/requirements.txt
downloadx/cmd/__init__.py
downloadx/cmd/__main__.py
downloadx/cmd/instagram_cli.py
downloadx/cmd/youtube_cli.py
downloadx/helpers/enums.py
downloadx/helpers/strings.py
downloadx/utils/__init__.py
downloadx/utils/youtube.py
downloadx-0.1.2.dist-info/METADATA
downloadx-0.1.2.dist-info/WHEEL
downloadx-0.1.2.dist-info/entry_points.txt
downloadx-0.1.2.dist-info/top_level.txt
downloadx-0.1.2.dist-info/RECORD
