Metadata-Version: 2.1
Name: downloadx
Version: 0.1.2
Summary: DownloadX CLI - Content download CLI tools
Author-email: ruriazz <azizruri.s@gmail.com>
Project-URL: Homepage, https://github.com/ruriazz/downloadx
Project-URL: Bug Tracker, https://github.com/ruriazz/downloadx/issues
Keywords: downloadx,DownloadX
Classifier: Operating System :: OS Independent
Classifier: Programming Language :: Python
Classifier: Programming Language :: Python :: 3.10
Requires-Python: >=3.10
Requires-Dist: alive-progress (==3.1.4)
Requires-Dist: pydantic (==1.10.8)
Requires-Dist: pytube (==15.0.0)
